qpiai_opt/__init__.py
qpiai_opt/problem/__init__.py
qpiai_opt/problem/max_cut.py
qpiai_opt/problem/max_independet_set.py
qpiai_opt/problem/number_partition.py
qpiai_opt/problem/qubo.py
qpiai_opt/problem/vertex_cover.py
qpiai_opt/solver/__init__.py
qpiai_opt/solver/solver.py
qpiai_opt/wrappers/__init__.py
qpiai_opt/wrappers/dwave.py
qpiai_opt/wrappers/qiskit.py
qpiai_opt_api-1.0.6.dist-info/LICENSE.txt
qpiai_opt_api-1.0.6.dist-info/METADATA
qpiai_opt_api-1.0.6.dist-info/WHEEL
qpiai_opt_api-1.0.6.dist-info/top_level.txt
qpiai_opt_api-1.0.6.dist-info/RECORD
