Metadata-Version: 2.1
Name: qpiai-opt-api
Version: 1.0.6
Summary: QpiAI-Opt-API is a an interface python package to access QpiAI-Opt solvers on cloud
Home-page: https://gitlab.qpiai.tech/qpiquantum/optimisation/qpiai-opt-api/
Author: Sagar B Dollin
Project-URL: Bug Tracker, https://gitlab.qpiai.tech/qpiquantum/optimisation/qpiai-opt-api/-/issues
Project-URL: repository, https://gitlab.qpiai.tech/qpiquantum/optimisation/qpiai-opt-api/
Classifier: Programming Language :: Python :: 3
Classifier: License :: OSI Approved :: MIT License
Classifier: Operating System :: OS Independent
Requires-Python: >=3.8
License-File: LICENSE.txt
